MANIFEST.in
setup.py
muzha/__init__.py
muzha/fahai.py
muzha/tianchuang.py
muzha/tongdun.py
muzha/wangxinzicha.py
muzha.egg-info/PKG-INFO
muzha.egg-info/SOURCES.txt
muzha.egg-info/dependency_links.txt
muzha.egg-info/requires.txt
muzha.egg-info/top_level.txt
muzha/authentication/__init__.py
muzha/authentication/auth_mongo.py
muzha/authentication/auth_mysql.py
muzha/authentication/base.py
muzha/authentication/file.py
muzha/bangsheng/__init__.py
muzha/bangsheng/base.py
muzha/bangsheng/lend_detail.py
muzha/bangsheng/loan_detail.py
muzha/bangsheng/loan_risk.py
muzha/bangsheng/overdue_detail.py
muzha/booldata/__init__.py
muzha/booldata/bankcard3eles.py
muzha/booldata/bankcard4eles.py
muzha/booldata/bankcard5eles.py
muzha/booldata/base.py
muzha/booldata/hz_risk_model.py
muzha/booldata/multi_platforms_v2.py
muzha/booldata/network3eles.py
muzha/booldata/ocr_idcard.py
muzha/booldata/person_law.py
muzha/booldata/personal_certify.py
muzha/booldata/template_hz_risk_model_v02.xlsx
muzha/huadao/__init__.py
muzha/ocr/__init__.py
muzha/ocr/cloud_walk/__init__.py
muzha/ocr/cloud_walk/bankcard.py
muzha/ocr/cloud_walk/base.py
muzha/ocr/cloud_walk/biz_license.py
muzha/ocr/cloud_walk/idcard.py
muzha/shanghaishuhe/__init__.py
muzha/shanghaishuhe/base.py
muzha/shenxin/__init__.py
muzha/shenxin/bankcard_five_elements.py
muzha/shenxin/base.py
muzha/shuhemofang/__init__.py
muzha/shuhemofang/base.py
muzha/shuhemofang/network_triple_elements.py
muzha/sms/__init__.py
muzha/sms/zhutong.py
muzha/suixingfu/__init__.py
muzha/suixingfu/bankcard_four_elements.py
muzha/suixingfu/bankcard_triple_elements.py
muzha/suixingfu/base.py
muzha/suixingfu/merchant_fraud_blacklist.py
muzha/suixingfu/network_triple_elements.py
muzha/tonglian/__init__.py
muzha/tonglian/base.py
muzha/tonglian/merchant_fraud_blacklist.py
muzha/xinyan/__init__.py
muzha/xinyan/base.py