Metadata-Version: 1.0
Name: muzha
Version: 0.0.27
Summary: muzha, nezha's brother
Home-page: UNKNOWN
Author: UNKNOWN
Author-email: UNKNOWN
License: UNKNOWN
Platform: UNKNOWN
